cheXwhatsApp/__init__.py
cheXwhatsApp/li_score.py
cheXwhatsApp/lung_segmentation.py
cheXwhatsApp/ols_score.py
cheXwhatsApp/pip_score.py
cheXwhatsApp-0.0.9.dist-info/LICENCE.txt
cheXwhatsApp-0.0.9.dist-info/METADATA
cheXwhatsApp-0.0.9.dist-info/WHEEL
cheXwhatsApp-0.0.9.dist-info/top_level.txt
cheXwhatsApp-0.0.9.dist-info/RECORD
