Metadata-Version: 2.1
Name: cheXwhatsApp
Version: 0.0.9
Author: Sahil Lathiya
Author-email: sahilm@iisc.ac.in
Classifier: Programming Language :: Python :: 3
Classifier: License :: OSI Approved :: MIT License
Classifier: Operating System :: OS Independent
License-File: LICENCE.txt
Requires-Dist: torch
Requires-Dist: imageio
Requires-Dist: scikit-image
Requires-Dist: numpy
Requires-Dist: tqdm
Requires-Dist: pandas
